capture/__init__.py
capture/capture.py
todoist_capture-1.0.4.dist-info/LICENSE
todoist_capture-1.0.4.dist-info/METADATA
todoist_capture-1.0.4.dist-info/WHEEL
todoist_capture-1.0.4.dist-info/entry_points.txt
todoist_capture-1.0.4.dist-info/top_level.txt
todoist_capture-1.0.4.dist-info/RECORD
