Metadata-Version: 2.1
Name: todoist-capture
Version: 1.0.4
Summary: Capture tasks to your Inbox from command line
Home-page: https://github.com/egegunes/todoist-capture
Author: Ege Güneş
Author-email: egegunes@gmail.com
License: GPLv3
Platform: UNKNOWN
Requires-Dist: todoist-python (==7.0.18)
